LICENSE.txt
setup.py
Saeed967.egg-info/PKG-INFO
Saeed967.egg-info/SOURCES.txt
Saeed967.egg-info/dependency_links.txt
Saeed967.egg-info/top_level.txt
code/__init__.py