Metadata-Version: 2.1
Name: Saeed967
Version: 0.1
Summary: library in python
Author: Saeed Algaradi
License-File: LICENSE.txt
